stopwatch/__init__.py
stopwatch/lap.py
stopwatch/profile.py
stopwatch/py.typed
stopwatch/statistics.py
stopwatch/stopwatch.py
stopwatch/utils.py
python_stopwatch2-1.1.1.dist-info/LICENSE
python_stopwatch2-1.1.1.dist-info/WHEEL
python_stopwatch2-1.1.1.dist-info/METADATA
python_stopwatch2-1.1.1.dist-info/RECORD
