Metadata-Version: 2.1
Name: python-stopwatch2
Version: 1.1.1
Summary: A simple library to measure code performance.
Home-page: https://stopwatch2.vercel.app/
License: MIT
Keywords: stopwatch,timer,time,profile
Author: Rafael
Author-email: contact.devrma@gmail.com
Maintainer: Rafael
Maintainer-email: contact.devrma@gmail.com
Requires-Python: >=3.7,<4.0
Classifier: License :: OSI Approved :: MIT License
Classifier: Programming Language :: Python :: 3
Classifier: Programming Language :: Python :: 3.10
Classifier: Programming Language :: Python :: 3.7
Classifier: Programming Language :: Python :: 3.8
Classifier: Programming Language :: Python :: 3.9
Requires-Dist: colorama (>=0.4.4,<0.5.0)
Project-URL: Documentation, https://stopwatch2.vercel.app/guide/getting-started.html
Project-URL: Repository, https://github.com/devRMA/python-stopwatch2
